urlblocks/__init__.py
urlblocks/compat.py
urlblocks/domain_levels.py
urlblocks/netloc.py
urlblocks/path.py
urlblocks/ports.py
urlblocks/query_string.py
urlblocks/six.py
urlblocks/urlblocks.py
urlblocks-0.1.dist-info/DESCRIPTION.rst
urlblocks-0.1.dist-info/METADATA
urlblocks-0.1.dist-info/metadata.json
urlblocks-0.1.dist-info/RECORD
urlblocks-0.1.dist-info/top_level.txt
urlblocks-0.1.dist-info/WHEEL
