Metadata-Version: 2.0
Name: urlblocks
Version: 0.1
Summary: urlblocks is the module provided URL string class which can be operated as a constructor, consisting of some blocks - URL components.
Home-page: http://github.com/vartagg/urlblocks
Author: Vladimir Chub
Author-email: vartagg@users.noreply.github.com
License: UNKNOWN
Platform: UNKNOWN
Classifier: Programming Language :: Python :: 2
Classifier: Programming Language :: Python :: 3
